terminal_buddy/__init__.py
terminal_buddy/main.py
terminal_buddy/utils/__init__.py
terminal_buddy/utils/config.py
terminal_buddy/utils/example_selection.py
terminal_buddy/utils/llm_functions.py
terminal_buddy/utils/prompts.py
terminal_buddy-0.1.2.dist-info/LICENSE
terminal_buddy-0.1.2.dist-info/METADATA
terminal_buddy-0.1.2.dist-info/WHEEL
terminal_buddy-0.1.2.dist-info/entry_points.txt
terminal_buddy-0.1.2.dist-info/RECORD
